dtreeplt/__init__.py
dtreeplt/dtreeplt.py
dtreeplt/interactive.py
dtreeplt-0.1.43.dist-info/LICENSE
dtreeplt-0.1.43.dist-info/METADATA
dtreeplt-0.1.43.dist-info/WHEEL
dtreeplt-0.1.43.dist-info/top_level.txt
dtreeplt-0.1.43.dist-info/RECORD
