Metadata-Version: 2.1
Name: dtreeplt
Version: 0.1.43
Summary: Visualize Decision Tree without Graphviz.
Home-page: https://github.com/nekoumei/dtreeplt
Author: nekoumei
Author-email: nekoumei@gmail.com
Maintainer: nekoumei
Maintainer-email: nekoumei@gmail.com
License: MIT
Platform: UNKNOWN
Classifier: Programming Language :: Python :: 3.6
Classifier: License :: OSI Approved :: MIT License
Classifier: Development Status :: 4 - Beta
Classifier: Environment :: MacOS X
Classifier: Topic :: Scientific/Engineering :: Artificial Intelligence
